animatedledstrip/__init__.py
animatedledstrip/als_http_client.py
animatedledstrip/animation_info.py
animatedledstrip/animation_to_run_params.py
animatedledstrip/color_container.py
animatedledstrip/distance.py
animatedledstrip/equation.py
animatedledstrip/json_decoder.py
animatedledstrip/json_encoder.py
animatedledstrip/location.py
animatedledstrip/new_animation_group_info.py
animatedledstrip/rotation.py
animatedledstrip/running_animation_params.py
animatedledstrip/section.py
animatedledstrip/strip_info.py
test/__init__.py
test/animatedledstrip/__init__.py
test/animatedledstrip/test_animation_info.py
test/animatedledstrip/test_colorcontainer.py
test/animatedledstrip/test_section.py
test/animatedledstrip/test_strip_info.py
animatedledstrip_client-1.1.0.dist-info/LICENSE
animatedledstrip_client-1.1.0.dist-info/METADATA
animatedledstrip_client-1.1.0.dist-info/WHEEL
animatedledstrip_client-1.1.0.dist-info/top_level.txt
animatedledstrip_client-1.1.0.dist-info/RECORD
