Metadata-Version: 2.1
Name: animatedledstrip-client
Version: 1.1.0
Summary: Library for communicating with an AnimatedLEDStrip server
Home-page: https://github.com/AnimatedLEDStrip/client-python
Author: Max Narvaez
Author-email: mnmax.narvaez3@gmail.com
License: MIT
License-File: LICENSE
